fake_module/__init__.py
fake_module/exceptions.py
fake_module/fake_module.py
fake_module-1.0.0.dist-info/LICENSE.md
fake_module-1.0.0.dist-info/METADATA
fake_module-1.0.0.dist-info/WHEEL
fake_module-1.0.0.dist-info/top_level.txt
fake_module-1.0.0.dist-info/RECORD
