Metadata-Version: 2.1
Name: fake-module
Version: 1.0.0
Summary: Globally replace a module with a configurable fake.
Home-page: https://github.com/joellefkowitz/fake-module
Author: Joel Lefkowitz
Author-email: joellefkowitz@hotmail.com
License: UNKNOWN
Project-URL: Bug Tracker, https://github.com/joellefkowitz/fake-module/issues
Project-URL: CI, https://github.com/joellefkowitz/fake-module/actions
Project-URL: Documentation, https://fake-module.readthedocs.io/en/latest/
Project-URL: Source Code, https://github.com/joellefkowitz/fake-module
Keywords: fake,module
Platform: UNKNOWN
Classifier: Intended Audience :: Developers
Classifier: License :: OSI Approved :: MIT License
Classifier: Programming Language :: Python :: 3.6
Classifier: Programming Language :: Python :: 3.7
Classifier: Programming Language :: Python :: 3.8
Classifier: Programming Language :: Python :: 3.9
Classifier: Operating System :: OS Independent
Classifier: Topic :: Software Development :: Libraries :: Python Modules
Requires-Python: >=3.6
Requires-Dist: dataclasses
Requires-Dist: types-dataclasses
Provides-Extra: all
Requires-Dist: coverage ; extra == 'all'
Requires-Dist: wheel ; extra == 'all'
Requires-Dist: mypy ; extra == 'all'
Requires-Dist: bump2version ; extra == 'all'
Requires-Dist: tox ; extra == 'all'
Requires-Dist: autoflake ; extra == 'all'
Requires-Dist: bandit ; extra == 'all'
Requires-Dist: isort ; extra == 'all'
Requires-Dist: quickdocs ; extra == 'all'
Requires-Dist: pytest ; extra == 'all'
Requires-Dist: black ; extra == 'all'
Requires-Dist: pylint ; extra == 'all'
Requires-Dist: twine ; extra == 'all'
Provides-Extra: docs
Requires-Dist: quickdocs ; extra == 'docs'
Provides-Extra: formatters
Requires-Dist: autoflake ; extra == 'formatters'
Requires-Dist: black ; extra == 'formatters'
Requires-Dist: isort ; extra == 'formatters'
Provides-Extra: linters
Requires-Dist: mypy ; extra == 'linters'
Requires-Dist: pylint ; extra == 'linters'
Requires-Dist: bandit ; extra == 'linters'
Provides-Extra: publishers
Requires-Dist: twine ; extra == 'publishers'
Requires-Dist: wheel ; extra == 'publishers'
Requires-Dist: bump2version ; extra == 'publishers'
Provides-Extra: tests
Requires-Dist: tox ; extra == 'tests'
Requires-Dist: coverage ; extra == 'tests'
Requires-Dist: pytest ; extra == 'tests'
